{"UIdata":[{"type":"joystick","size":250,"color":"#ffcb13","posX":320,"posY":710,"buttonPressedVal":null,"buttonReleasedVal":null,"keyboardKeys":["d","a","w","s"],"gamepadAxes":[],"dataIndices":["0","1"],"recenter":true},{"type":"number indicator","size":250,"colorHigh":"#5fad47","colorLow":"#d73920","colorHighVal":3.7,"colorLowVal":3.5,"posX":350,"posY":0,"labelText":"","dataIndices":["0"]},{"type":"number indicator","size":250,"colorHigh":"#808080","colorLow":"#808080","colorHighVal":1,"colorLowVal":0,"posX":30,"posY":320,"labelText":"l vel","dataIndices":["1"]},{"type":"number indicator","size":250,"colorHigh":"#808080","colorLow":"#808080","colorHighVal":1,"colorLowVal":0,"posX":320,"posY":320,"labelText":"r vel","dataIndices":["2"]}]}